gpfy/__init__.py
gpfy/gegenbauer.py
gpfy/likelihoods.py
gpfy/model.py
gpfy/optimization.py
gpfy/param.py
gpfy/quadrature.py
gpfy/scan.py
gpfy/spherical.py
gpfy/spherical_harmonics.py
gpfy/training.py
gpfy/typing.py
gpfy/utils.py
gpfy/variational.py
gpfy/fundamental_system/__init__.py
gpfy/fundamental_system/fs_10D.npz
gpfy/fundamental_system/fs_11D.npz
gpfy/fundamental_system/fs_12D.npz
gpfy/fundamental_system/fs_13D.npz
gpfy/fundamental_system/fs_14D.npz
gpfy/fundamental_system/fs_15D.npz
gpfy/fundamental_system/fs_16D.npz
gpfy/fundamental_system/fs_17D.npz
gpfy/fundamental_system/fs_18D.npz
gpfy/fundamental_system/fs_19D.npz
gpfy/fundamental_system/fs_20D.npz
gpfy/fundamental_system/fs_3D.npz
gpfy/fundamental_system/fs_4D.npz
gpfy/fundamental_system/fs_5D.npz
gpfy/fundamental_system/fs_6D.npz
gpfy/fundamental_system/fs_7D.npz
gpfy/fundamental_system/fs_8D.npz
gpfy/fundamental_system/fs_9D.npz
gpfy/harmonics/__init__.py
gpfy/harmonics/fund_set.py
gpfy/harmonics/utils.py
gpfy-0.7.0.dist-info/licenses/LICENSE
gpfy-0.7.0.dist-info/METADATA
gpfy-0.7.0.dist-info/WHEEL
gpfy-0.7.0.dist-info/top_level.txt
gpfy-0.7.0.dist-info/RECORD
