Metadata-Version: 2.4
Name: gpfy
Version: 0.7.0
Summary: Gaussian process with spherical harmonic features in JAX
Author-email: Stefanos Eleftheriadis <stelefth@gmail.com>
License: Apache-2.0
Keywords: gaussian process,spherical harmonics,jax
Classifier: License :: OSI Approved :: Apache Software License
Classifier: Programming Language :: Python :: 3.8
Requires-Python: <3.14,>=3.11
License-File: LICENSE
Requires-Dist: jax
Requires-Dist: jaxlib
Requires-Dist: tfp-nightly
Requires-Dist: numpy
Requires-Dist: scipy
Requires-Dist: optax
Requires-Dist: jaxtyping>=0.2.15
Requires-Dist: tqdm
Requires-Dist: datasets
Provides-Extra: dev
Requires-Dist: autoflake; extra == "dev"
Requires-Dist: black; extra == "dev"
Requires-Dist: flake8; extra == "dev"
Requires-Dist: isort>=5.1; extra == "dev"
Requires-Dist: mypy>=0.920; extra == "dev"
Requires-Dist: pytest-cov; extra == "dev"
Requires-Dist: pytest-random-order; extra == "dev"
Requires-Dist: pytest-xdist; extra == "dev"
Requires-Dist: pytest>=3.5.0; extra == "dev"
Requires-Dist: ipykernel; extra == "dev"
Requires-Dist: ipython; extra == "dev"
Requires-Dist: jupyter_client; extra == "dev"
Requires-Dist: notebook; extra == "dev"
Requires-Dist: jupytext; extra == "dev"
Requires-Dist: nbconvert; extra == "dev"
Requires-Dist: nbformat; extra == "dev"
Requires-Dist: matplotlib>=3.7.1; extra == "dev"
Dynamic: license-file
